megalite/__init__.py
megalite/bot.py
megalite/core.py
megalite/simpletools.py
megalite/train.py
megalite/utils.py
megarnucleusx-0.0.5.0.dist-info/METADATA
megarnucleusx-0.0.5.0.dist-info/WHEEL
megarnucleusx-0.0.5.0.dist-info/top_level.txt
megarnucleusx-0.0.5.0.dist-info/RECORD
