Metadata-Version: 2.4
Name: megarnucleusx
Version: 0.0.5.0
Summary: Una IA modular de alto nivel con bots pre-configurados, impulsada por sminitorch y micronumpy.
Home-page: https://github.com/TuUsuario/megarnucleusx
Author: TuNombre
Author-email: tu@email.com
Classifier: Programming Language :: Python :: 3
Classifier: License :: OSI Approved :: MIT License
Classifier: Operating System :: OS Independent
Classifier: Topic :: Scientific/Engineering :: Artificial Intelligence
Classifier: Development Status :: 4 - Beta
Requires-Python: >=3.6
Requires-Dist: sminitorch>=0.1.0
Requires-Dist: micronumpy>=0.1.2
Dynamic: author
Dynamic: author-email
Dynamic: classifier
Dynamic: description
Dynamic: description-content-type
Dynamic: home-page
Dynamic: requires-dist
Dynamic: requires-python
Dynamic: summary
